[
  {
    "title": "dsf",
    "id": 1580722606476,
    "todoItems": [
      {"id": 1580722606476, "isDone": false, "item": "sss"},
      {"id": 1580722606476, "isDone": false, "item": "ss"}
    ]
  },
  {
    "title": "dsf",
    "id": 1580722599550,
    "todoItems": [
      {"id": 1580722599550, "isDone": false, "item": "fffff"},
      {"id": 1580722599550, "isDone": false, "item": "fffff"}
    ]
  },
  {
    "title": "dsfdsfs",
    "id": 1580722525851,
    "todoItems": [{"id": 1580722525851, "isDone": false, "item": "dfsdfdsfsdf"}]
  },
  {
    "title": "ssdf",
    "id": 1580722436952,
    "todoItems": [{"isDone": false, "item": "sdfds"}]
  },
  {
    "title": "ras",
    "id": 1580722396340,
    "todoItems": [{"isDone": false, "item": "dgd"}]
  },
  {
    "title": "sdf",
    "id": 1580722391072,
    "todoItems": [{"isDone": false, "item": "ras"}]
  }
]
